recalibrate/__init__.py
recalibrate/nothing.py
recalibrate-0.0.3.dist-info/LICENSE
recalibrate-0.0.3.dist-info/METADATA
recalibrate-0.0.3.dist-info/WHEEL
recalibrate-0.0.3.dist-info/entry_points.txt
recalibrate-0.0.3.dist-info/top_level.txt
recalibrate-0.0.3.dist-info/RECORD
